.gitignore
MANIFEST.in
NOTES.md
README.md
UNLICENSE
setup.cfg
setup.py
/Users/thruflo/Development/pyramid/torque_engine/.gitignore
/Users/thruflo/Development/pyramid/torque_engine/MANIFEST.in
/Users/thruflo/Development/pyramid/torque_engine/NOTES.md
/Users/thruflo/Development/pyramid/torque_engine/README.md
/Users/thruflo/Development/pyramid/torque_engine/UNLICENSE
/Users/thruflo/Development/pyramid/torque_engine/setup.cfg
/Users/thruflo/Development/pyramid/torque_engine/setup.py
/Users/thruflo/Development/pyramid/torque_engine/src/pyramid_torque_engine/__init__.py
/Users/thruflo/Development/pyramid/torque_engine/src/pyramid_torque_engine/action.py
/Users/thruflo/Development/pyramid/torque_engine/src/pyramid_torque_engine/auth.py
/Users/thruflo/Development/pyramid/torque_engine/src/pyramid_torque_engine/client.py
/Users/thruflo/Development/pyramid/torque_engine/src/pyramid_torque_engine/constants.py
/Users/thruflo/Development/pyramid/torque_engine/src/pyramid_torque_engine/interfaces.py
/Users/thruflo/Development/pyramid/torque_engine/src/pyramid_torque_engine/machine.py
/Users/thruflo/Development/pyramid/torque_engine/src/pyramid_torque_engine/operations.py
/Users/thruflo/Development/pyramid/torque_engine/src/pyramid_torque_engine/orm.py
/Users/thruflo/Development/pyramid/torque_engine/src/pyramid_torque_engine/render.py
/Users/thruflo/Development/pyramid/torque_engine/src/pyramid_torque_engine/repo.py
/Users/thruflo/Development/pyramid/torque_engine/src/pyramid_torque_engine/subscribe.py
/Users/thruflo/Development/pyramid/torque_engine/src/pyramid_torque_engine/transition.py
/Users/thruflo/Development/pyramid/torque_engine/src/pyramid_torque_engine/traverse.py
/Users/thruflo/Development/pyramid/torque_engine/src/pyramid_torque_engine/unpack.py
/Users/thruflo/Development/pyramid/torque_engine/src/pyramid_torque_engine/util.py
/Users/thruflo/Development/pyramid/torque_engine/src/pyramid_torque_engine/view.py
src/pyramid_torque_engine.egg-info/PKG-INFO
src/pyramid_torque_engine.egg-info/SOURCES.txt
src/pyramid_torque_engine.egg-info/dependency_links.txt
src/pyramid_torque_engine.egg-info/not-zip-safe
src/pyramid_torque_engine.egg-info/requires.txt
src/pyramid_torque_engine.egg-info/top_level.txt
