Metadata-Version: 1.1
Name: pyramid-torque-engine
Version: 0.2
Summary: Pyramid and nTorque based dual queue work engine system.
Home-page: http://github.com/thruflo/pyramid_torque_engine
Author: James Arthur
Author-email: username: thruflo, domain: gmail.com
License: UNKNOWN
Platform: UNKNOWN
Classifier: Development Status :: 3 - Alpha
Classifier: Environment :: Web Environment
Classifier: Intended Audience :: Developers
Classifier: License :: Public Domain
Classifier: Natural Language :: English
Classifier: Operating System :: OS Independent
Classifier: Programming Language :: Python
Classifier: Programming Language :: Python :: 2.7
Classifier: Framework :: Pylons
Classifier: Topic :: Internet :: WWW/HTTP :: WSGI
